[
    {
        "start":  "2025-05-02T00:30:00.0000000",
        "title":  "Concrete Utopia",
        "end":  "2025-05-02T02:45:00.0000000"
    },
    {
        "start":  "2025-05-02T02:45:00.0000000",
        "title":  "Biosphere",
        "end":  "2025-05-02T04:35:00.0000000"
    },
    {
        "start":  "2025-05-02T04:35:00.0000000",
        "title":  "Silent Running",
        "end":  "2025-05-02T06:20:00.0000000"
    },
    {
        "start":  "2025-05-02T06:20:00.0000000",
        "title":  "The Little Rascals",
        "end":  "2025-05-02T07:50:00.0000000"
    },
    {
        "start":  "2025-05-02T07:50:00.0000000",
        "title":  "Death Becomes Her",
        "end":  "2025-05-02T09:35:00.0000000"
    },
    {
        "start":  "2025-05-02T09:35:00.0000000",
        "title":  "Dumb \u0026 Dumber",
        "end":  "2025-05-02T11:25:00.0000000"
    },
    {
        "start":  "2025-05-02T11:25:00.0000000",
        "title":  "Naked Gun: From The Files of Police Squad!",
        "end":  "2025-05-02T12:55:00.0000000"
    },
    {
        "start":  "2025-05-02T12:55:00.0000000",
        "title":  "The Naked Gun 2 1/2: The Smell Of Fear",
        "end":  "2025-05-02T14:25:00.0000000"
    },
    {
        "start":  "2025-05-02T14:25:00.0000000",
        "title":  "Forrest Gump",
        "end":  "2025-05-02T16:50:00.0000000"
    },
    {
        "start":  "2025-05-02T16:50:00.0000000",
        "title":  "The Karate Kid",
        "end":  "2025-05-02T19:00:00.0000000"
    },
    {
        "start":  "2025-05-02T19:00:00.0000000",
        "title":  "Back To The Future",
        "end":  "2025-05-02T21:00:00.0000000"
    },
    {
        "start":  "2025-05-02T21:00:00.0000000",
        "title":  "Mission: Impossible - Dead Reckoning",
        "end":  "2025-05-02T23:45:00.0000000"
    },
    {
        "start":  "2025-05-02T23:45:00.0000000",
        "title":  "Bad Boys",
        "end":  "2025-05-03T00:00:00.0000000"
    },
    {
        "start":  "2025-05-03T01:45:00.0000000",
        "title":  "Dumb \u0026 Dumber",
        "end":  "2025-05-03T03:35:00.0000000"
    },
    {
        "start":  "2025-05-03T03:35:00.0000000",
        "title":  "The Little Rascals",
        "end":  "2025-05-03T05:00:00.0000000"
    },
    {
        "start":  "2025-05-03T05:00:00.0000000",
        "title":  "Adventures Of Tom Thumb And  Thumbelina",
        "end":  "2025-05-03T06:20:00.0000000"
    },
    {
        "start":  "2025-05-03T06:20:00.0000000",
        "title":  "Forrest Gump",
        "end":  "2025-05-03T08:45:00.0000000"
    },
    {
        "start":  "2025-05-03T08:45:00.0000000",
        "title":  "Back To The Future",
        "end":  "2025-05-03T10:45:00.0000000"
    },
    {
        "start":  "2025-05-03T10:45:00.0000000",
        "title":  "The Karate Kid",
        "end":  "2025-05-03T12:55:00.0000000"
    },
    {
        "start":  "2025-05-03T12:55:00.0000000",
        "title":  "Airplane!",
        "end":  "2025-05-03T14:25:00.0000000"
    },
    {
        "start":  "2025-05-03T14:25:00.0000000",
        "title":  "Mission: Impossible - Dead Reckoning",
        "end":  "2025-05-03T17:10:00.0000000"
    },
    {
        "start":  "2025-05-03T17:10:00.0000000",
        "title":  "Back To The Future Part II",
        "end":  "2025-05-03T19:00:00.0000000"
    },
    {
        "start":  "2025-05-03T19:00:00.0000000",
        "title":  "Barbie",
        "end":  "2025-05-03T21:00:00.0000000"
    },
    {
        "start":  "2025-05-03T21:00:00.0000000",
        "title":  "Bad Boys",
        "end":  "2025-05-04T00:00:00.0000000"
    },
    {
        "start":  "2025-05-03T01:45:00.0000000",
        "title":  "Dumb \u0026 Dumber",
        "end":  "2025-05-03T03:35:00.0000000"
    },
    {
        "start":  "2025-05-03T03:35:00.0000000",
        "title":  "The Little Rascals",
        "end":  "2025-05-03T05:00:00.0000000"
    },
    {
        "start":  "2025-05-03T05:00:00.0000000",
        "title":  "Adventures Of Tom Thumb And  Thumbelina",
        "end":  "2025-05-03T06:20:00.0000000"
    },
    {
        "start":  "2025-05-03T06:20:00.0000000",
        "title":  "Forrest Gump",
        "end":  "2025-05-03T08:45:00.0000000"
    },
    {
        "start":  "2025-05-03T08:45:00.0000000",
        "title":  "Back To The Future",
        "end":  "2025-05-03T10:45:00.0000000"
    },
    {
        "start":  "2025-05-03T10:45:00.0000000",
        "title":  "The Karate Kid",
        "end":  "2025-05-03T12:55:00.0000000"
    },
    {
        "start":  "2025-05-03T12:55:00.0000000",
        "title":  "Airplane!",
        "end":  "2025-05-03T14:25:00.0000000"
    },
    {
        "start":  "2025-05-03T14:25:00.0000000",
        "title":  "Mission: Impossible - Dead Reckoning",
        "end":  "2025-05-03T17:10:00.0000000"
    },
    {
        "start":  "2025-05-03T17:10:00.0000000",
        "title":  "Back To The Future Part II",
        "end":  "2025-05-03T19:00:00.0000000"
    },
    {
        "start":  "2025-05-03T19:00:00.0000000",
        "title":  "Barbie",
        "end":  "2025-05-03T21:00:00.0000000"
    },
    {
        "start":  "2025-05-03T21:00:00.0000000",
        "title":  "Bad Boys",
        "end":  "2025-05-04T00:00:00.0000000"
    },
    {
        "start":  "2025-05-02T00:30:00.0000000",
        "title":  "Concrete Utopia",
        "end":  "2025-05-02T02:45:00.0000000"
    },
    {
        "start":  "2025-05-02T02:45:00.0000000",
        "title":  "Biosphere",
        "end":  "2025-05-02T04:35:00.0000000"
    },
    {
        "start":  "2025-05-02T04:35:00.0000000",
        "title":  "Silent Running",
        "end":  "2025-05-02T06:20:00.0000000"
    },
    {
        "start":  "2025-05-02T06:20:00.0000000",
        "title":  "The Little Rascals",
        "end":  "2025-05-02T07:50:00.0000000"
    },
    {
        "start":  "2025-05-02T07:50:00.0000000",
        "title":  "Death Becomes Her",
        "end":  "2025-05-02T09:35:00.0000000"
    },
    {
        "start":  "2025-05-02T09:35:00.0000000",
        "title":  "Dumb \u0026 Dumber",
        "end":  "2025-05-02T11:25:00.0000000"
    },
    {
        "start":  "2025-05-02T11:25:00.0000000",
        "title":  "Naked Gun: From The Files of Police Squad!",
        "end":  "2025-05-02T12:55:00.0000000"
    },
    {
        "start":  "2025-05-02T12:55:00.0000000",
        "title":  "The Naked Gun 2 1/2: The Smell Of Fear",
        "end":  "2025-05-02T14:25:00.0000000"
    },
    {
        "start":  "2025-05-02T14:25:00.0000000",
        "title":  "Forrest Gump",
        "end":  "2025-05-02T16:50:00.0000000"
    },
    {
        "start":  "2025-05-02T16:50:00.0000000",
        "title":  "The Karate Kid",
        "end":  "2025-05-02T19:00:00.0000000"
    },
    {
        "start":  "2025-05-02T19:00:00.0000000",
        "title":  "Back To The Future",
        "end":  "2025-05-02T21:00:00.0000000"
    },
    {
        "start":  "2025-05-02T21:00:00.0000000",
        "title":  "Mission: Impossible - Dead Reckoning",
        "end":  "2025-05-02T23:45:00.0000000"
    },
    {
        "start":  "2025-05-02T23:45:00.0000000",
        "title":  "Bad Boys",
        "end":  "2025-05-03T00:00:00.0000000"
    },
    {
        "start":  "2025-05-03T01:45:00.0000000",
        "title":  "Dumb \u0026 Dumber",
        "end":  "2025-05-03T03:35:00.0000000"
    },
    {
        "start":  "2025-05-03T03:35:00.0000000",
        "title":  "The Little Rascals",
        "end":  "2025-05-03T05:00:00.0000000"
    },
    {
        "start":  "2025-05-03T05:00:00.0000000",
        "title":  "Adventures Of Tom Thumb And  Thumbelina",
        "end":  "2025-05-03T06:20:00.0000000"
    },
    {
        "start":  "2025-05-03T06:20:00.0000000",
        "title":  "Forrest Gump",
        "end":  "2025-05-03T08:45:00.0000000"
    },
    {
        "start":  "2025-05-03T08:45:00.0000000",
        "title":  "Back To The Future",
        "end":  "2025-05-03T10:45:00.0000000"
    },
    {
        "start":  "2025-05-03T10:45:00.0000000",
        "title":  "The Karate Kid",
        "end":  "2025-05-03T12:55:00.0000000"
    },
    {
        "start":  "2025-05-03T12:55:00.0000000",
        "title":  "Airplane!",
        "end":  "2025-05-03T14:25:00.0000000"
    },
    {
        "start":  "2025-05-03T14:25:00.0000000",
        "title":  "Mission: Impossible - Dead Reckoning",
        "end":  "2025-05-03T17:10:00.0000000"
    },
    {
        "start":  "2025-05-03T17:10:00.0000000",
        "title":  "Back To The Future Part II",
        "end":  "2025-05-03T19:00:00.0000000"
    },
    {
        "start":  "2025-05-03T19:00:00.0000000",
        "title":  "Barbie",
        "end":  "2025-05-03T21:00:00.0000000"
    },
    {
        "start":  "2025-05-03T21:00:00.0000000",
        "title":  "Bad Boys",
        "end":  "2025-05-04T00:00:00.0000000"
    }
]