[
    {
        "start":  "2025-04-30T07:00:00.0000000",
        "title":  "לזכרם",
        "end":  "2025-04-30T11:00:00.0000000"
    },
    {
        "start":  "2025-04-30T11:00:00.0000000",
        "title":  "לזכרם",
        "end":  "2025-04-30T15:00:00.0000000"
    },
    {
        "start":  "2025-04-30T15:00:00.0000000",
        "title":  "לזכרם",
        "end":  "2025-04-30T16:45:00.0000000"
    },
    {
        "start":  "2025-04-30T16:45:00.0000000",
        "title":  "ישיר! טקס הדלקת המשואות",
        "end":  "2025-04-30T18:35:00.0000000"
    },
    {
        "start":  "2025-04-30T18:35:00.0000000",
        "title":  "אגדה מקומית - רן בן שמעון",
        "end":  "2025-04-30T19:15:00.0000000"
    },
    {
        "start":  "2025-04-30T19:15:00.0000000",
        "title":  "אגדה מקומית - טל ברודי",
        "end":  "2025-04-30T19:55:00.0000000"
    },
    {
        "start":  "2025-04-30T19:55:00.0000000",
        "title":  "אגדה מקומית - שלמה שרף",
        "end":  "2025-04-30T20:35:00.0000000"
    },
    {
        "start":  "2025-04-30T20:35:00.0000000",
        "title":  "אגדה מקומית - אריק זאבי",
        "end":  "2025-04-30T21:15:00.0000000"
    },
    {
        "start":  "2025-04-30T21:15:00.0000000",
        "title":  "אגדה מקומית - עודד מכנס",
        "end":  "2025-04-30T22:00:00.0000000"
    },
    {
        "start":  "2025-04-30T22:00:00.0000000",
        "title":  "אגדה מקומית - יעל ארד",
        "end":  "2025-04-30T22:45:00.0000000"
    },
    {
        "start":  "2025-04-30T22:45:00.0000000",
        "title":  "אגדה מקומית - ארטיום דולגופיאט",
        "end":  "2025-04-30T23:25:00.0000000"
    },
    {
        "start":  "2025-04-30T23:25:00.0000000",
        "title":  "אגדה מקומית - מורן סמואל",
        "end":  "2025-04-30T23:55:00.0000000"
    },
    {
        "start":  "2025-04-30T23:55:00.0000000",
        "title":  "אגדה מקומית - יוסי מזרחי",
        "end":  "2025-05-01T00:40:00.0000000"
    },
    {
        "start":  "2025-05-01T00:40:00.0000000",
        "title":  "אגדה מקומית - בועז ינאי",
        "end":  "2025-05-01T01:20:00.0000000"
    },
    {
        "start":  "2025-05-01T01:20:00.0000000",
        "title":  "אגדה מקומית - אברהם קליין",
        "end":  "2025-05-01T01:55:00.0000000"
    },
    {
        "start":  "2025-05-01T01:55:00.0000000",
        "title":  "אגדה מקומית - איציק ויסוקר",
        "end":  "2025-05-01T02:35:00.0000000"
    },
    {
        "start":  "2025-05-01T02:35:00.0000000",
        "title":  "אגדה מקומית - אורנה אוסטפלד",
        "end":  "2025-05-01T03:00:00.0000000"
    },
    {
        "start":  "2025-05-01T03:00:00.0000000",
        "title":  "בובה של לילה 8",
        "end":  "2025-05-01T03:55:00.0000000"
    },
    {
        "start":  "2025-05-01T03:55:00.0000000",
        "title":  "בובה של לילה 8",
        "end":  "2025-05-01T04:55:00.0000000"
    },
    {
        "start":  "2025-05-01T04:55:00.0000000",
        "title":  "בובה של לילה 8",
        "end":  "2025-05-01T05:55:00.0000000"
    },
    {
        "start":  "2025-05-01T05:55:00.0000000",
        "title":  "בובה של לילה 8",
        "end":  "2025-05-01T06:45:00.0000000"
    },
    {
        "start":  "2025-05-01T06:45:00.0000000",
        "title":  "בובה של לילה 8",
        "end":  "2025-05-01T07:45:00.0000000"
    },
    {
        "start":  "2025-05-01T07:45:00.0000000",
        "title":  "בובה של לילה 8",
        "end":  "2025-05-01T08:40:00.0000000"
    },
    {
        "start":  "2025-05-01T08:40:00.0000000",
        "title":  "בובה של לילה 8",
        "end":  "2025-05-01T09:00:00.0000000"
    },
    {
        "start":  "2025-05-01T09:00:00.0000000",
        "title":  "בובה של לילה 8",
        "end":  "2025-05-01T09:20:00.0000000"
    },
    {
        "start":  "2025-05-01T09:20:00.0000000",
        "title":  "בובה של לילה 8",
        "end":  "2025-05-01T10:25:00.0000000"
    },
    {
        "start":  "2025-05-01T10:25:00.0000000",
        "title":  "ישיר! יובה סטאביה - קטנזארו",
        "end":  "2025-05-01T12:30:00.0000000"
    },
    {
        "start":  "2025-05-01T12:30:00.0000000",
        "title":  "בובה של לילה 8",
        "end":  "2025-05-01T12:55:00.0000000"
    },
    {
        "start":  "2025-05-01T12:55:00.0000000",
        "title":  "ישיר! סמפדוריה - קרמונזה",
        "end":  "2025-05-01T15:00:00.0000000"
    },
    {
        "start":  "2025-05-01T15:00:00.0000000",
        "title":  "בובה של לילה 8",
        "end":  "2025-05-01T19:00:00.0000000"
    },
    {
        "start":  "2025-05-01T19:00:00.0000000",
        "title":  "בובה של לילה 8",
        "end":  "2025-05-01T23:00:00.0000000"
    },
    {
        "start":  "2025-05-01T23:00:00.0000000",
        "title":  "בובה של לילה 8",
        "end":  "2025-05-02T03:15:00.0000000"
    },
    {
        "start":  "2025-05-02T03:15:00.0000000",
        "title":  "ארסנל - פ.ס.ז\u0027",
        "end":  "2025-05-02T05:00:00.0000000"
    },
    {
        "start":  "2025-05-02T05:00:00.0000000",
        "title":  "ברצלונה - אינטר",
        "end":  "2025-05-02T06:45:00.0000000"
    },
    {
        "start":  "2025-05-02T06:45:00.0000000",
        "title":  "פילדלפיה - וושינגטון",
        "end":  "2025-05-02T07:00:00.0000000"
    },
    {
        "start":  "2025-05-02T07:00:00.0000000",
        "title":  "ל.א. איינג\u0027לס - דטרויט",
        "end":  "2025-05-02T07:15:00.0000000"
    },
    {
        "start":  "2025-05-02T07:15:00.0000000",
        "title":  "סאסואולו - קרארזה",
        "end":  "2025-05-02T07:35:00.0000000"
    },
    {
        "start":  "2025-05-02T07:35:00.0000000",
        "title":  "בית\u0027\u0027ר י-ם - מ. חיפה",
        "end":  "2025-05-02T08:20:00.0000000"
    },
    {
        "start":  "2025-05-02T08:20:00.0000000",
        "title":  "אגדה מקומית - ספיישל עצמאות",
        "end":  "2025-05-02T09:05:00.0000000"
    },
    {
        "start":  "2025-05-02T09:05:00.0000000",
        "title":  "אגדה מקומית - ספיישל עצמאות",
        "end":  "2025-05-02T09:50:00.0000000"
    },
    {
        "start":  "2025-05-02T09:50:00.0000000",
        "title":  "ישיר! ל. לאומית בכדורסל",
        "end":  "2025-05-02T12:00:00.0000000"
    },
    {
        "start":  "2025-05-02T12:00:00.0000000",
        "title":  "ישיר! ל. הכדוריד",
        "end":  "2025-05-02T14:15:00.0000000"
    },
    {
        "start":  "2025-05-02T14:15:00.0000000",
        "title":  "אגדה מקומית - ספיישל עצמאות",
        "end":  "2025-05-02T15:00:00.0000000"
    },
    {
        "start":  "2025-05-02T15:00:00.0000000",
        "title":  "אגדה מקומית - ספיישל עצמאות",
        "end":  "2025-05-02T15:55:00.0000000"
    },
    {
        "start":  "2025-05-02T15:55:00.0000000",
        "title":  "ישיר! אלמאטי - קרטגנה",
        "end":  "2025-05-02T18:05:00.0000000"
    },
    {
        "start":  "2025-05-02T18:05:00.0000000",
        "title":  "ברצלונה - אינטר",
        "end":  "2025-05-02T18:20:00.0000000"
    },
    {
        "start":  "2025-05-02T18:20:00.0000000",
        "title":  "בובה של לילה 8",
        "end":  "2025-05-02T18:40:00.0000000"
    },
    {
        "start":  "2025-05-02T18:40:00.0000000",
        "title":  "ישיר! ניס - ריימס",
        "end":  "2025-05-02T20:45:00.0000000"
    },
    {
        "start":  "2025-05-02T20:45:00.0000000",
        "title":  "ה. י-ם - מ. ר\u0027\u0027ג, מ. 1",
        "end":  "2025-05-02T22:20:00.0000000"
    },
    {
        "start":  "2025-05-02T22:20:00.0000000",
        "title":  "אגדה מקומית - ספיישל עצמאות",
        "end":  "2025-05-02T23:05:00.0000000"
    },
    {
        "start":  "2025-05-02T23:05:00.0000000",
        "title":  "אגדה מקומית - ספיישל עצמאות",
        "end":  "2025-05-02T23:50:00.0000000"
    },
    {
        "start":  "2025-05-02T23:50:00.0000000",
        "title":  "יש מצב בשישי",
        "end":  "2025-05-03T00:55:00.0000000"
    },
    {
        "start":  "2025-05-03T00:55:00.0000000",
        "title":  "ערוץ הקיבוץ, מחזור 35",
        "end":  "2025-05-03T03:40:00.0000000"
    },
    {
        "start":  "2025-05-03T03:40:00.0000000",
        "title":  "ניס - ריימס",
        "end":  "2025-05-03T05:25:00.0000000"
    },
    {
        "start":  "2025-05-03T05:25:00.0000000",
        "title":  "ה. י-ם - מ. ר\u0027\u0027ג, מ. 1",
        "end":  "2025-05-03T07:00:00.0000000"
    },
    {
        "start":  "2025-05-03T07:00:00.0000000",
        "title":  "אטלנטה - ל.א. דודג\u0027רס",
        "end":  "2025-05-03T07:15:00.0000000"
    },
    {
        "start":  "2025-05-03T07:15:00.0000000",
        "title":  "סן פרנסיסקו - קולורדו",
        "end":  "2025-05-03T07:30:00.0000000"
    },
    {
        "start":  "2025-05-03T07:30:00.0000000",
        "title":  "ספורטינג - פאלמה",
        "end":  "2025-05-03T07:50:00.0000000"
    },
    {
        "start":  "2025-05-03T07:50:00.0000000",
        "title":  "יש מצב בשישי",
        "end":  "2025-05-03T08:55:00.0000000"
    },
    {
        "start":  "2025-05-03T08:55:00.0000000",
        "title":  "בית\u0027\u0027ר י-ם - מ. חיפה",
        "end":  "2025-05-03T09:20:00.0000000"
    },
    {
        "start":  "2025-05-03T09:20:00.0000000",
        "title":  "ל. הכדוריד",
        "end":  "2025-05-03T10:55:00.0000000"
    },
    {
        "start":  "2025-05-03T10:55:00.0000000",
        "title":  "יש מצב בשישי",
        "end":  "2025-05-03T12:00:00.0000000"
    },
    {
        "start":  "2025-05-03T12:00:00.0000000",
        "title":  "ג\u0027ודו",
        "end":  "2025-05-03T14:05:00.0000000"
    },
    {
        "start":  "2025-05-03T14:05:00.0000000",
        "title":  "יש מצב בשישי",
        "end":  "2025-05-03T15:10:00.0000000"
    },
    {
        "start":  "2025-05-03T15:10:00.0000000",
        "title":  "ברצלונה - אינטר",
        "end":  "2025-05-03T15:30:00.0000000"
    },
    {
        "start":  "2025-05-03T15:30:00.0000000",
        "title":  "פלייאוף NBA",
        "end":  "2025-05-03T17:45:00.0000000"
    },
    {
        "start":  "2025-05-03T17:45:00.0000000",
        "title":  "ליגת ווינר סל",
        "end":  "2025-05-03T20:05:00.0000000"
    },
    {
        "start":  "2025-05-03T20:05:00.0000000",
        "title":  "בני ריינה - ה. חדרה",
        "end":  "2025-05-03T21:50:00.0000000"
    },
    {
        "start":  "2025-05-03T21:50:00.0000000",
        "title":  "ליגת ווינר סל",
        "end":  "2025-05-03T23:25:00.0000000"
    },
    {
        "start":  "2025-05-03T23:25:00.0000000",
        "title":  "ה. ק\u0027\u0027ש - בני סכנין",
        "end":  "2025-05-04T01:10:00.0000000"
    },
    {
        "start":  "2025-05-04T01:10:00.0000000",
        "title":  "סנט אטיין - מונאקו",
        "end":  "2025-05-04T01:11:00.0000000"
    }
]